{"textures":{"0":"modelengine:entity/xenomorph_drone","particle":"#0"},"elements":[{"from":[4.5,7.950001,5.5],"to":[11.5,13.950001,10.5],"faces":{"east":{"uv":[4.125,1.75,4.75,2.5],"tintindex":0,"rotation":0,"texture":"#0"},"south":{"uv":[1.5,2.375,2.375,3.125],"tintindex":0,"rotation":0,"texture":"#0"},"north":{"uv":[0.625,2.375,1.5,3.125],"tintindex":0,"rotation":0,"texture":"#0"},"west":{"uv":[4.125,3.625,4.75,4.375],"tintindex":0,"rotation":0,"texture":"#0"},"up":{"uv":[2.75,3.75,1.875,3.125],"tintindex":0,"rotation":0,"texture":"#0"},"down":{"uv":[3.625,3.125,2.75,3.75],"tintindex":0,"rotation":0,"texture":"#0"}}},{"from":[4.25,7.700001,5.25],"to":[11.75,14.200001,10.75],"faces":{"east":{"uv":[1.75,4.25,2.375,5.0],"tintindex":0,"rotation":0,"texture":"#0"},"south":{"uv":[2.75,0.0,3.625,0.75],"tintindex":0,"rotation":0,"texture":"#0"},"north":{"uv":[2.375,2.375,3.25,3.125],"tintindex":0,"rotation":0,"texture":"#0"},"west":{"uv":[4.125,4.375,4.75,5.125],"tintindex":0,"rotation":0,"texture":"#0"},"up":{"uv":[4.125,2.625,3.25,2.0],"tintindex":0,"rotation":0,"texture":"#0"},"down":{"uv":[4.5,0.0,3.625,0.625],"tintindex":0,"rotation":0,"texture":"#0"}}},{"from":[8.0,7.950001,6.5],"to":[8.0,13.950001,11.5],"faces":{"east":{"uv":[0.0,9.5,0.625,10.25],"tintindex":0,"rotation":0,"texture":"#0"},"west":{"uv":[0.0,8.75,0.625,9.5],"tintindex":0,"rotation":0,"texture":"#0"}}}],"display":{"head":{"rotation":[0.0,0.0,0.0]},"firstperson_righthand":{"rotation":[0.0,0.0,0.0]},"thirdperson_lefthand":{"rotation":[0.0,0.0,0.0]},"firstperson_lefthand":{"rotation":[0.0,0.0,0.0]},"fixed":{"rotation":[0.0,0.0,0.0]},"ground":{"rotation":[0.0,0.0,0.0]},"thirdperson_righthand":{"rotation":[0.0,0.0,0.0]},"gui":{"rotation":[-150.0,-45.0,180.0]}}}