{"model":{"type":"range_dispatch","property":"custom_model_data","index":0,"fallback":{"type":"minecraft:model","model":"minecraft:item/apple"},"entries":[{"threshold":409,"model":{"type":"model","model":"infinitecrops:item/crops/tomato/tomato"}},{"threshold":410,"model":{"type":"model","model":"infinitecrops:item/crops/tomato/tomato_ametish_star"}},{"threshold":411,"model":{"type":"model","model":"infinitecrops:item/crops/tomato/tomato_golden_star"}},{"threshold":412,"model":{"type":"model","model":"infinitecrops:item/crops/tomato/tomato_rotten"}},{"threshold":413,"model":{"type":"model","model":"infinitecrops:item/crops/tomato/tomato_silver_star"}},{"threshold":422,"model":{"type":"model","model":"infinitecrops:item/crops/pitaya/pitaya"}},{"threshold":423,"model":{"type":"model","model":"infinitecrops:item/crops/pitaya/pitaya_ametish_star"}},{"threshold":424,"model":{"type":"model","model":"infinitecrops:item/crops/pitaya/pitaya_golden_star"}},{"threshold":425,"model":{"type":"model","model":"infinitecrops:item/crops/pitaya/pitaya_rotten"}},{"threshold":426,"model":{"type":"model","model":"infinitecrops:item/crops/pitaya/pitaya_silver_star"}},{"threshold":436,"model":{"type":"model","model":"infinitecrops:item/crops/pepper/pepper"}},{"threshold":437,"model":{"type":"model","model":"infinitecrops:item/crops/pepper/pepper_ametish_star"}},{"threshold":438,"model":{"type":"model","model":"infinitecrops:item/crops/pepper/pepper_golden_star"}},{"threshold":439,"model":{"type":"model","model":"infinitecrops:item/crops/pepper/pepper_rotten"}},{"threshold":440,"model":{"type":"model","model":"infinitecrops:item/crops/pepper/pepper_silver_star"}},{"threshold":447,"model":{"type":"model","model":"infinitecrops:item/crops/pineapple/pineapple"}},{"threshold":448,"model":{"type":"model","model":"infinitecrops:item/crops/pineapple/pineapple_ametish_star"}},{"threshold":449,"model":{"type":"model","model":"infinitecrops:item/crops/pineapple/pineapple_golden_star"}},{"threshold":450,"model":{"type":"model","model":"infinitecrops:item/crops/pineapple/pineapple_rotten"}},{"threshold":451,"model":{"type":"model","model":"infinitecrops:item/crops/pineapple/pineapple_silver_star"}},{"threshold":459,"model":{"type":"model","model":"infinitecrops:item/crops/corn/corn"}},{"threshold":460,"model":{"type":"model","model":"infinitecrops:item/crops/corn/corn_ametish_star"}},{"threshold":461,"model":{"type":"model","model":"infinitecrops:item/crops/corn/corn_golden_star"}},{"threshold":462,"model":{"type":"model","model":"infinitecrops:item/crops/corn/corn_rotten"}},{"threshold":463,"model":{"type":"model","model":"infinitecrops:item/crops/corn/corn_silver_star"}},{"threshold":471,"model":{"type":"model","model":"infinitecrops:item/crops/garlic/garlic"}},{"threshold":472,"model":{"type":"model","model":"infinitecrops:item/crops/garlic/garlic_ametish_star"}},{"threshold":473,"model":{"type":"model","model":"infinitecrops:item/crops/garlic/garlic_golden_star"}},{"threshold":474,"model":{"type":"model","model":"infinitecrops:item/crops/garlic/garlic_rotten"}},{"threshold":475,"model":{"type":"model","model":"infinitecrops:item/crops/garlic/garlic_silver_star"}},{"threshold":484,"model":{"type":"model","model":"infinitecrops:item/crops/eggplant/eggplant"}},{"threshold":485,"model":{"type":"model","model":"infinitecrops:item/crops/eggplant/eggplant_ametish_star"}},{"threshold":486,"model":{"type":"model","model":"infinitecrops:item/crops/eggplant/eggplant_golden_star"}},{"threshold":487,"model":{"type":"model","model":"infinitecrops:item/crops/eggplant/eggplant_rotten"}},{"threshold":488,"model":{"type":"model","model":"infinitecrops:item/crops/eggplant/eggplant_silver_star"}},{"threshold":500,"model":{"type":"model","model":"infinitecrops:item/crops/apple_tree/apple_ametish_star"}},{"threshold":501,"model":{"type":"model","model":"infinitecrops:item/crops/apple_tree/apple_golden_star"}},{"threshold":502,"model":{"type":"model","model":"infinitecrops:item/crops/apple_tree/apple_rotten"}},{"threshold":503,"model":{"type":"model","model":"infinitecrops:item/crops/apple_tree/apple_silver_star"}},{"threshold":510,"model":{"type":"model","model":"infinitecrops:item/crops/chinese_cabbage/chinese_cabbage"}},{"threshold":511,"model":{"type":"model","model":"infinitecrops:item/crops/chinese_cabbage/chinese_cabbage_ametish_star"}},{"threshold":512,"model":{"type":"model","model":"infinitecrops:item/crops/chinese_cabbage/chinese_cabbage_golden_star"}},{"threshold":513,"model":{"type":"model","model":"infinitecrops:item/crops/chinese_cabbage/chinese_cabbage_rotten"}},{"threshold":514,"model":{"type":"model","model":"infinitecrops:item/crops/chinese_cabbage/chinese_cabbage_silver_star"}},{"threshold":526,"model":{"type":"model","model":"infinitecrops:item/crops/orange_tree/orange"}},{"threshold":527,"model":{"type":"model","model":"infinitecrops:item/crops/orange_tree/orange_ametish_star"}},{"threshold":528,"model":{"type":"model","model":"infinitecrops:item/crops/orange_tree/orange_golden_star"}},{"threshold":529,"model":{"type":"model","model":"infinitecrops:item/crops/orange_tree/orange_rotten"}},{"threshold":530,"model":{"type":"model","model":"infinitecrops:item/crops/orange_tree/orange_silver_star"}},{"threshold":537,"model":{"type":"model","model":"infinitecrops:item/crops/cabbage/cabbage"}},{"threshold":538,"model":{"type":"model","model":"infinitecrops:item/crops/cabbage/cabbage_ametish_star"}},{"threshold":539,"model":{"type":"model","model":"infinitecrops:item/crops/cabbage/cabbage_golden_star"}},{"threshold":540,"model":{"type":"model","model":"infinitecrops:item/crops/cabbage/cabbage_rotten"}},{"threshold":541,"model":{"type":"model","model":"infinitecrops:item/crops/cabbage/cabbage_silver_star"}},{"threshold":550,"model":{"type":"model","model":"infinitecrops:item/crops/grape/grape"}},{"threshold":551,"model":{"type":"model","model":"infinitecrops:item/crops/grape/grape_ametish_star"}},{"threshold":552,"model":{"type":"model","model":"infinitecrops:item/crops/grape/grape_golden_star"}},{"threshold":553,"model":{"type":"model","model":"infinitecrops:item/crops/grape/grape_rotten"}},{"threshold":554,"model":{"type":"model","model":"infinitecrops:item/crops/grape/grape_silver_star"}},{"threshold":562,"model":{"type":"model","model":"infinitecrops:item/crops/hop/hop"}},{"threshold":563,"model":{"type":"model","model":"infinitecrops:item/crops/hop/hop_ametish_star"}},{"threshold":564,"model":{"type":"model","model":"infinitecrops:item/crops/hop/hop_golden_star"}},{"threshold":565,"model":{"type":"model","model":"infinitecrops:item/crops/hop/hop_rotten"}},{"threshold":566,"model":{"type":"model","model":"infinitecrops:item/crops/hop/hop_silver_star"}},{"threshold":10000,"model":{"type":"model","model":"iasurvival:ia_auto_gen/pear"}},{"threshold":10001,"model":{"type":"model","model":"iasurvival:ia_auto_gen/tomato"}},{"threshold":10002,"model":{"type":"model","model":"iasurvival:ia_auto_gen/rice"}},{"threshold":10003,"model":{"type":"model","model":"iasurvival:ia_auto_gen/lettuce"}},{"threshold":10004,"model":{"type":"model","model":"iasurvival:ia_auto_gen/chili_pepper"}},{"threshold":10005,"model":{"type":"model","model":"iasurvival:ia_auto_gen/banana"}},{"threshold":10006,"model":{"type":"model","model":"iasurvival:ia_auto_gen/garlic"}},{"threshold":10007,"model":{"type":"model","model":"item/apple"}}]},"oversized_in_gui":true}